[
  {
    "id": "kuhou_001",
    "question": "「不可不学」の書き下し文として最も適切なものを選べ。",
    "choices": [
      "学ばざるべからず",
      "学ぶべからず",
      "学ばざらんや",
      "学ぶこと能はず"
    ],
    "answer": 0,
    "explanation": "「不可不～」は二重否定で「～しないわけにはいかない・～しなければならない」の意。打消の「ず」＋当然の「べし」の打消＝「ざるべからず」。早稲田・難関私大頻出の句形。"
  },
  {
    "id": "kuhou_002",
    "question": "反語形「豈～乎（あニ～ンヤ）」の意味として最も適切なものを選べ。",
    "choices": [
      "どうして～か、いや～ない",
      "どうして～なのか、その理由を問う",
      "もしかしたら～かもしれない",
      "～してはどうか（勧誘）"
    ],
    "answer": 0,
    "explanation": "「豈～乎・哉」は反語の代表形。「どうして～か、いや～ない」と強い否定を意味する。疑問形と紛らわしいが、文脈上「答えがNOに決まっている」場合は反語。早稲田頻出。"
  },
  {
    "id": "kuhou_003",
    "question": "使役の句形「使A B」の意味として最も適切なものを選べ。",
    "choices": [
      "AにBをさせる",
      "AはBである",
      "AをBに変える",
      "AのためにBする"
    ],
    "answer": 0,
    "explanation": "「使・令・遣・教」＋A＋B（動詞）で使役を表す。「AをしてB（せ）しむ」と読み、「AにBさせる」の意。例：「使臣往（臣をして往かしむ）」。漢文の基本句形で必修。"
  },
  {
    "id": "kuhou_004",
    "question": "限定の句形「唯～耳（たダ～ノミ）」の意味として最も適切なものを選べ。",
    "choices": [
      "ただ～だけだ",
      "～にすぎないだろうか",
      "～できるのみ",
      "ただ～しただけだ"
    ],
    "answer": 0,
    "explanation": "「唯（ただ）」「特」「但」などと文末「耳・爾・而已（のみ）」の組み合わせで限定を表す。「ただ～だけだ」の意。例：「唯仁者能愛人耳」＝ただ仁者のみ能く人を愛するのみ。"
  },
  {
    "id": "kuhou_005",
    "question": "比較の句形「A 不如 B」の意味として最も適切なものを選べ。",
    "choices": [
      "AはBに及ばない",
      "AはBと同じである",
      "AはBより優れる",
      "AはBに似ている"
    ],
    "answer": 0,
    "explanation": "「不如（しカず）」は比較の句形で「～に及ばない」。「A不如B」＝AはBに及ばない＝Bのほうがよい。「百聞不如一見」＝百聞は一見にしかず。「莫如（しクハなシ）」は最上級で「～に及ぶものはない」。"
  }
]
